{
  "id": "minimum-array-end",
  "title": "Minimum Array End",
  "difficulty": "Medium",
  "tags": [
    "Bit Manipulation"
  ],
  "description": "You are given two integers n and x. You have to construct an array of positive integers nums of size n where for every 0 <= i < n - 1, nums[i + 1] is greater than nums[i], and the result of the bitwise AND operation between all elements of nums is x.\nReturn the minimum possible value of nums[n - 1].\n\u00a0\nExample 1:\n\nInput: n = 3, x = 4\nOutput: 6\nExplanation:\nnums can be [4,5,6] and its last element is 6.\n\nExample 2:\n\nInput: n = 2, x = 7\nOutput: 15\nExplanation:\nnums can be [7,15] and its last element is 15.\n\n\u00a0\nConstraints:\n\n1 <= n, x <= 108\n\n",
  "entry_point": "Solution().minEnd",
  "starter_code": "class Solution:\n    def minEnd(self, n: int, x: int) -> int:\n        ",
  "preamble": "from typing import *\nfrom collections import *\nfrom functools import *\nfrom itertools import *\nfrom heapq import *\nfrom bisect import *\nfrom math import *\nimport math, collections, functools, itertools, bisect, heapq, string, re\n",
  "check_function": "def check(candidate):\n    assert candidate(n = 4,x = 8) == 11\n    assert candidate(n = 5,x = 1) == 9\n    assert candidate(n = 10,x = 1) == 19\n    assert candidate(n = 5,x = 3) == 19\n    assert candidate(n = 2,x = 7) == 15\n    assert candidate(n = 1,x = 10) == 10\n    assert candidate(n = 10,x = 16) == 25\n    assert candidate(n = 1,x = 5) == 5\n    assert candidate(n = 1,x = 32) == 32\n    assert candidate(n = 3,x = 4) == 6\n    assert candidate(n = 500000,x = 256) == 1000223\n    assert candidate(n = 30,x = 2048) == 2077\n    assert candidate(n = 500000,x = 2047) == 1023999999\n    assert candidate(n = 50,x = 512) == 561\n    assert candidate(n = 100,x = 128) == 227\n    assert candidate(n = 8,x = 4096) == 4103\n    assert candidate(n = 20,x = 8) == 43\n    assert candidate(n = 100000,x = 65535) == 6553599999\n    assert candidate(n = 512,x = 32768) == 33279\n    assert candidate(n = 7,x = 12) == 30\n    assert candidate(n = 15,x = 8) == 30\n    assert candidate(n = 4,x = 3) == 15\n    assert candidate(n = 20,x = 16) == 51\n    assert candidate(n = 8,x = 3) == 31\n    assert candidate(n = 12,x = 3) == 47\n    assert candidate(n = 1,x = 1073741824) == 1073741824\n    assert candidate(n = 1000,x = 512) == 2023\n    assert candidate(n = 8,x = 1023) == 8191\n    assert candidate(n = 100000000,x = 1073741823) == 107374182399999999\n    assert candidate(n = 100,x = 16) == 211\n    assert candidate(n = 30,x = 17) == 123\n    assert candidate(n = 30,x = 64) == 93\n    assert candidate(n = 15,x = 31) == 479\n    assert candidate(n = 100,x = 255) == 25599\n    assert candidate(n = 4,x = 63) == 255\n    assert candidate(n = 5,x = 1023) == 5119\n    assert candidate(n = 10,x = 1024) == 1033\n    assert candidate(n = 8,x = 7) == 63\n    assert candidate(n = 5,x = 8) == 12\n    assert candidate(n = 50000,x = 31) == 1599999\n    assert candidate(n = 9,x = 512) == 520\n    assert candidate(n = 4,x = 15) == 63\n    assert candidate(n = 6,x = 2048) == 2053\n    assert candidate(n = 7,x = 10) == 30\n    assert candidate(n = 15,x = 100) == 126\n    assert candidate(n = 6,x = 10) == 27\n    assert candidate(n = 3,x = 16) == 18\n    assert candidate(n = 50,x = 2048) == 2097\n    assert candidate(n = 1000,x = 4096) == 5095\n    assert candidate(n = 10,x = 1048575) == 10485759\n    assert candidate(n = 15,x = 1024) == 1038\n    assert candidate(n = 50,x = 128) == 177\n    assert candidate(n = 20,x = 2047) == 40959\n    assert candidate(n = 25,x = 2048) == 2072\n    assert candidate(n = 6,x = 24) == 29\n    assert candidate(n = 7,x = 128) == 134\n    assert candidate(n = 100,x = 1047552) == 1047651\n    assert candidate(n = 15,x = 512) == 526\n    assert candidate(n = 3,x = 12) == 14\n    assert candidate(n = 20,x = 512) == 531\n    assert candidate(n = 1,x = 1023) == 1023\n    assert candidate(n = 100000,x = 1023) == 102399999\n    assert candidate(n = 3,x = 31) == 95\n    assert candidate(n = 5,x = 31) == 159\n    assert candidate(n = 50,x = 31) == 1599\n    assert candidate(n = 500,x = 512) == 1011\n    assert candidate(n = 10000000,x = 4095) == 40959999999\n    assert candidate(n = 64,x = 2048) == 2111\n    assert candidate(n = 8,x = 32) == 39\n    assert candidate(n = 3,x = 13) == 29\n    assert candidate(n = 8,x = 31) == 255\n    assert candidate(n = 7,x = 64) == 70\n    assert candidate(n = 1,x = 1024) == 1024\n    assert candidate(n = 1024,x = 65535) == 67108863\n    assert candidate(n = 100,x = 4096) == 4195\n    assert candidate(n = 7,x = 1024) == 1030\n    assert candidate(n = 9,x = 256) == 264\n    assert candidate(n = 1000,x = 2048) == 3047\n    assert candidate(n = 10,x = 32) == 41\n    assert candidate(n = 50,x = 255) == 12799\n    assert candidate(n = 100000,x = 128) == 200095\n    assert candidate(n = 100000,x = 1) == 199999\n    assert candidate(n = 8,x = 255) == 2047\n    assert candidate(n = 5,x = 15) == 79\n    assert candidate(n = 100,x = 256) == 355\n    assert candidate(n = 25,x = 128) == 152\n    assert candidate(n = 6,x = 64) == 69\n    assert candidate(n = 7,x = 32) == 38\n    assert candidate(n = 5,x = 12) == 28\n    assert candidate(n = 1,x = 2048) == 2048\n    assert candidate(n = 2,x = 1073741823) == 2147483647\n    assert candidate(n = 14,x = 1023) == 14335\n    assert candidate(n = 50,x = 1024) == 1073\n    assert candidate(n = 200,x = 8192) == 8391\n    assert candidate(n = 128,x = 16383) == 2097151\n    assert candidate(n = 20,x = 3) == 79\n    assert candidate(n = 11,x = 512) == 522\n    assert candidate(n = 10,x = 256) == 265\n    assert candidate(n = 1,x = 8191) == 8191\n    assert candidate(n = 1,x = 1048575) == 1048575\n    assert candidate(n = 30,x = 8191) == 245759\n    assert candidate(n = 4,x = 17) == 23\n    assert candidate(n = 5,x = 10) == 26\n    assert candidate(n = 30,x = 512) == 541\n    assert candidate(n = 15,x = 7) == 119\n    assert candidate(n = 9,x = 255) == 2303\n",
  "test_cases": [
    "assert candidate(n = 4,x = 8) == 11",
    "assert candidate(n = 5,x = 1) == 9",
    "assert candidate(n = 10,x = 1) == 19",
    "assert candidate(n = 5,x = 3) == 19",
    "assert candidate(n = 2,x = 7) == 15",
    "assert candidate(n = 1,x = 10) == 10",
    "assert candidate(n = 10,x = 16) == 25",
    "assert candidate(n = 1,x = 5) == 5",
    "assert candidate(n = 1,x = 32) == 32",
    "assert candidate(n = 3,x = 4) == 6",
    "assert candidate(n = 500000,x = 256) == 1000223",
    "assert candidate(n = 30,x = 2048) == 2077",
    "assert candidate(n = 500000,x = 2047) == 1023999999",
    "assert candidate(n = 50,x = 512) == 561",
    "assert candidate(n = 100,x = 128) == 227",
    "assert candidate(n = 8,x = 4096) == 4103",
    "assert candidate(n = 20,x = 8) == 43",
    "assert candidate(n = 100000,x = 65535) == 6553599999",
    "assert candidate(n = 512,x = 32768) == 33279",
    "assert candidate(n = 7,x = 12) == 30",
    "assert candidate(n = 15,x = 8) == 30",
    "assert candidate(n = 4,x = 3) == 15",
    "assert candidate(n = 20,x = 16) == 51",
    "assert candidate(n = 8,x = 3) == 31",
    "assert candidate(n = 12,x = 3) == 47",
    "assert candidate(n = 1,x = 1073741824) == 1073741824",
    "assert candidate(n = 1000,x = 512) == 2023",
    "assert candidate(n = 8,x = 1023) == 8191",
    "assert candidate(n = 100000000,x = 1073741823) == 107374182399999999",
    "assert candidate(n = 100,x = 16) == 211",
    "assert candidate(n = 30,x = 17) == 123",
    "assert candidate(n = 30,x = 64) == 93",
    "assert candidate(n = 15,x = 31) == 479",
    "assert candidate(n = 100,x = 255) == 25599",
    "assert candidate(n = 4,x = 63) == 255",
    "assert candidate(n = 5,x = 1023) == 5119",
    "assert candidate(n = 10,x = 1024) == 1033",
    "assert candidate(n = 8,x = 7) == 63",
    "assert candidate(n = 5,x = 8) == 12",
    "assert candidate(n = 50000,x = 31) == 1599999",
    "assert candidate(n = 9,x = 512) == 520",
    "assert candidate(n = 4,x = 15) == 63",
    "assert candidate(n = 6,x = 2048) == 2053",
    "assert candidate(n = 7,x = 10) == 30",
    "assert candidate(n = 15,x = 100) == 126",
    "assert candidate(n = 6,x = 10) == 27",
    "assert candidate(n = 3,x = 16) == 18",
    "assert candidate(n = 50,x = 2048) == 2097",
    "assert candidate(n = 1000,x = 4096) == 5095",
    "assert candidate(n = 10,x = 1048575) == 10485759",
    "assert candidate(n = 15,x = 1024) == 1038",
    "assert candidate(n = 50,x = 128) == 177",
    "assert candidate(n = 20,x = 2047) == 40959",
    "assert candidate(n = 25,x = 2048) == 2072",
    "assert candidate(n = 6,x = 24) == 29",
    "assert candidate(n = 7,x = 128) == 134",
    "assert candidate(n = 100,x = 1047552) == 1047651",
    "assert candidate(n = 15,x = 512) == 526",
    "assert candidate(n = 3,x = 12) == 14",
    "assert candidate(n = 20,x = 512) == 531",
    "assert candidate(n = 1,x = 1023) == 1023",
    "assert candidate(n = 100000,x = 1023) == 102399999",
    "assert candidate(n = 3,x = 31) == 95",
    "assert candidate(n = 5,x = 31) == 159",
    "assert candidate(n = 50,x = 31) == 1599",
    "assert candidate(n = 500,x = 512) == 1011",
    "assert candidate(n = 10000000,x = 4095) == 40959999999",
    "assert candidate(n = 64,x = 2048) == 2111",
    "assert candidate(n = 8,x = 32) == 39",
    "assert candidate(n = 3,x = 13) == 29",
    "assert candidate(n = 8,x = 31) == 255",
    "assert candidate(n = 7,x = 64) == 70",
    "assert candidate(n = 1,x = 1024) == 1024",
    "assert candidate(n = 1024,x = 65535) == 67108863",
    "assert candidate(n = 100,x = 4096) == 4195",
    "assert candidate(n = 7,x = 1024) == 1030",
    "assert candidate(n = 9,x = 256) == 264",
    "assert candidate(n = 1000,x = 2048) == 3047",
    "assert candidate(n = 10,x = 32) == 41",
    "assert candidate(n = 50,x = 255) == 12799",
    "assert candidate(n = 100000,x = 128) == 200095",
    "assert candidate(n = 100000,x = 1) == 199999",
    "assert candidate(n = 8,x = 255) == 2047",
    "assert candidate(n = 5,x = 15) == 79",
    "assert candidate(n = 100,x = 256) == 355",
    "assert candidate(n = 25,x = 128) == 152",
    "assert candidate(n = 6,x = 64) == 69",
    "assert candidate(n = 7,x = 32) == 38",
    "assert candidate(n = 5,x = 12) == 28",
    "assert candidate(n = 1,x = 2048) == 2048",
    "assert candidate(n = 2,x = 1073741823) == 2147483647",
    "assert candidate(n = 14,x = 1023) == 14335",
    "assert candidate(n = 50,x = 1024) == 1073",
    "assert candidate(n = 200,x = 8192) == 8391",
    "assert candidate(n = 128,x = 16383) == 2097151",
    "assert candidate(n = 20,x = 3) == 79",
    "assert candidate(n = 11,x = 512) == 522",
    "assert candidate(n = 10,x = 256) == 265",
    "assert candidate(n = 1,x = 8191) == 8191",
    "assert candidate(n = 1,x = 1048575) == 1048575",
    "assert candidate(n = 30,x = 8191) == 245759",
    "assert candidate(n = 4,x = 17) == 23",
    "assert candidate(n = 5,x = 10) == 26",
    "assert candidate(n = 30,x = 512) == 541",
    "assert candidate(n = 15,x = 7) == 119",
    "assert candidate(n = 9,x = 255) == 2303"
  ]
}