{
  "id": "minimum-number-of-food-buckets-to-feed-the-hamsters",
  "title": "Minimum Number Of Food Buckets To Feed The Hamsters",
  "difficulty": "Medium",
  "tags": [
    "Greedy",
    "String",
    "Dynamic Programming"
  ],
  "description": "You are given a 0-indexed string hamsters where hamsters[i] is either:\n\n'H' indicating that there is a hamster at index i, or\n'.' indicating that index i is empty.\n\nYou will add some number of food buckets at the empty indices in order to feed the hamsters. A hamster can be fed if there is at least one food bucket to its left or to its right. More formally, a hamster at index i can be fed if you place a food bucket at index i - 1 and/or at index i + 1.\nReturn the minimum number of food buckets you should place at empty indices to feed all the hamsters or -1 if it is impossible to feed all of them.\n\u00a0\nExample 1:\n\n\nInput: hamsters = \"H..H\"\nOutput: 2\nExplanation: We place two food buckets at indices 1 and 2.\nIt can be shown that if we place only one food bucket, one of the hamsters will not be fed.\n\nExample 2:\n\n\nInput: hamsters = \".H.H.\"\nOutput: 1\nExplanation: We place one food bucket at index 2.\n\nExample 3:\n\n\nInput: hamsters = \".HHH.\"\nOutput: -1\nExplanation: If we place a food bucket at every empty index as shown, the hamster at index 2 will not be able to eat.\n\n\u00a0\nConstraints:\n\n1 <= hamsters.length <= 105\nhamsters[i] is either'H' or '.'.\n\n",
  "entry_point": "Solution().minimumBuckets",
  "starter_code": "class Solution:\n    def minimumBuckets(self, hamsters: str) -> int:\n        ",
  "preamble": "from typing import *\nfrom collections import *\nfrom functools import *\nfrom itertools import *\nfrom heapq import *\nfrom bisect import *\nfrom math import *\nimport math, collections, functools, itertools, bisect, heapq, string, re\n",
  "check_function": "def check(candidate):\n    assert candidate(hamsters = \"H\") == -1\n    assert candidate(hamsters = \"H.H.H.H.H.H\") == 3\n    assert candidate(hamsters = \"HH.H.H.H.H.H.H.H.H.H.H.H.H.H\") == -1\n    assert candidate(hamsters = \"H.H.H.H.H.H.H.H.H.H\") == 5\n    assert candidate(hamsters = \".....\") == 0\n    assert candidate(hamsters = \".\") == 0\n    assert candidate(hamsters = \"H..H\") == 2\n    assert candidate(hamsters = \"H.H\") == 1\n    assert candidate(hamsters = \"H....H\") == 2\n    assert candidate(hamsters = \"H.H.H.H.H\") == 3\n    assert candidate(hamsters = \"HHHH\") == -1\n    assert candidate(hamsters = \"H.H.H.H.H.H.H\") == 4\n    assert candidate(hamsters = \"HH\") == -1\n    assert candidate(hamsters = \"H.H.HH\") == -1\n    assert candidate(hamsters = \".HHH.\") == -1\n    assert candidate(hamsters = \"HH.H.H.H.H.H.H.H.H.H.H.H.H.H.H.H.H.H\") == -1\n    assert candidate(hamsters = \"HH.H.H.H.H.H.H.H.H.H.H.H.H.H.H.H.H.H.H.H\") == -1\n    assert candidate(hamsters = \"H.H.H.H.H.H.H.H.H.H.H.H.H.H.H\") == 8\n    assert candidate(hamsters = \"HH.HH.HH\") == -1\n    assert candidate(hamsters = \"H.H.H\") == 2\n    assert candidate(hamsters = \"HH.H.H.H.H\") == -1\n    assert candidate(hamsters = \"H.H.H.H\") == 2\n    assert candidate(hamsters = \"HH.HH\") == -1\n    assert candidate(hamsters = \"HH.H.H.H.H.H.H.H.H.H.H\") == -1\n    assert candidate(hamsters = \"HH.H.H.H.H.H.H.H.H.H.H.H\") == -1\n    assert candidate(hamsters = \".H.H.\") == 1\n    assert candidate(hamsters = \"H.H.H.H.H.H.H.H\") == 4\n    assert candidate(hamsters = \"H.HH\") == -1\n    assert candidate(hamsters = \"H.H.H.H.H.H.H.H.H.H.H.H.H\") == 7\n    assert candidate(hamsters = \"HHHHHH\") == -1\n    assert candidate(hamsters = \"HH.H.H\") == -1\n    assert candidate(hamsters = \"HH.H\") == -1\n    assert candidate(hamsters = \"H.H.H.H.H.H.H.H.H\") == 5\n    assert candidate(hamsters = \"HH.H.H.H.H.H.H\") == -1\n    assert candidate(hamsters = \"H.H.H.H.H.H.H.H.H.H.H.H.H.H.H.H.H.H.H\") == 10\n    assert candidate(hamsters = \"HH.H.H.H.H.H.H.H.H.H.H.H.H.H.H.H\") == -1\n    assert candidate(hamsters = \"HH.H.HH\") == -1\n    assert candidate(hamsters = \"......\") == 0\n    assert candidate(hamsters = \"H.H.H.H.H.H.H.H.H.H.H\") == 6\n    assert candidate(hamsters = \"...\") == 0\n    assert candidate(hamsters = \"H.H.H.H.H.H.H.H.H.H.H.H.H.H.H.H.H\") == 9\n    assert candidate(hamsters = \"H.H.HH.H.H\") == 4\n    assert candidate(hamsters = \"H.....H\") == 2\n    assert candidate(hamsters = \"H.H.H.H.H.H.H\") == 4\n    assert candidate(hamsters = \"H.....H\") == 2\n    assert candidate(hamsters = \".......\") == 0\n    assert candidate(hamsters = \"HH.HHHHH.HH\") == -1\n    assert candidate(hamsters = \".H.H.\") == 1\n    assert candidate(hamsters = \"H.H.H.H.HH\") == -1\n    assert candidate(hamsters = \"........\") == 0\n    assert candidate(hamsters = \"H.H.H.H.H.H.H.H.H\") == 5\n    assert candidate(hamsters = \"..H.H..\") == 1\n    assert candidate(hamsters = \"H.H.H.H.H\") == 3\n    assert candidate(hamsters = \"HH.H.H.HH\") == -1\n    assert candidate(hamsters = \"HH\") == -1\n    assert candidate(hamsters = \"H.HH.H\") == 2\n    assert candidate(hamsters = \"HH.HH.HH.HH.HH.HH.HH.HH\") == -1\n    assert candidate(hamsters = \"...\") == 0\n    assert candidate(hamsters = \"H.\") == 1\n    assert candidate(hamsters = \"H.H..H.H\") == 2\n    assert candidate(hamsters = \"H.......H\") == 2\n    assert candidate(hamsters = \"..H..H..\") == 2\n    assert candidate(hamsters = \"HHHHH\") == -1\n    assert candidate(hamsters = \"HH.HH\") == -1\n    assert candidate(hamsters = \"HH.H.H.H.HH\") == -1\n    assert candidate(hamsters = \"H...H\") == 2\n    assert candidate(hamsters = \"HH.HHH.HH\") == -1\n    assert candidate(hamsters = \"........\") == 0\n    assert candidate(hamsters = \"H.H.H.HH.H\") == 3\n    assert candidate(hamsters = \"HH.HH.HH.HH\") == -1\n    assert candidate(hamsters = \"H.H.H.H\") == 2\n    assert candidate(hamsters = \".\") == 0\n    assert candidate(hamsters = \"HHHHHHHHHH\") == -1\n    assert candidate(hamsters = \".HHH.\") == -1\n    assert candidate(hamsters = \"H.H.H.HH\") == -1\n    assert candidate(hamsters = \".H\") == 1\n    assert candidate(hamsters = \".H.H.H.H.\") == 2\n    assert candidate(hamsters = \"H.H.H\") == 2\n    assert candidate(hamsters = \"H\") == -1\n    assert candidate(hamsters = \".........\") == 0\n    assert candidate(hamsters = \".H.H.H.H.H.H.H.H.H.\") == 5\n    assert candidate(hamsters = \".H.H.H.H.H.H.H.H.\") == 4\n    assert candidate(hamsters = \"HHHHHHH\") == -1\n    assert candidate(hamsters = \"HH...HH\") == -1\n    assert candidate(hamsters = \"H.H.H.H.H.H.H.H.H.H.H.H\") == 6\n    assert candidate(hamsters = \"H......H\") == 2\n    assert candidate(hamsters = \"H.H\") == 1\n    assert candidate(hamsters = \"HH.HH.HH.HH.HH\") == -1\n    assert candidate(hamsters = \"H..H\") == 2\n    assert candidate(hamsters = \"HH..HH\") == -1\n    assert candidate(hamsters = \"HHHH\") == -1\n",
  "test_cases": [
    "assert candidate(hamsters = \"H\") == -1",
    "assert candidate(hamsters = \"H.H.H.H.H.H\") == 3",
    "assert candidate(hamsters = \"HH.H.H.H.H.H.H.H.H.H.H.H.H.H\") == -1",
    "assert candidate(hamsters = \"H.H.H.H.H.H.H.H.H.H\") == 5",
    "assert candidate(hamsters = \".....\") == 0",
    "assert candidate(hamsters = \".\") == 0",
    "assert candidate(hamsters = \"H..H\") == 2",
    "assert candidate(hamsters = \"H.H\") == 1",
    "assert candidate(hamsters = \"H....H\") == 2",
    "assert candidate(hamsters = \"H.H.H.H.H\") == 3",
    "assert candidate(hamsters = \"HHHH\") == -1",
    "assert candidate(hamsters = \"H.H.H.H.H.H.H\") == 4",
    "assert candidate(hamsters = \"HH\") == -1",
    "assert candidate(hamsters = \"H.H.HH\") == -1",
    "assert candidate(hamsters = \".HHH.\") == -1",
    "assert candidate(hamsters = \"HH.H.H.H.H.H.H.H.H.H.H.H.H.H.H.H.H.H\") == -1",
    "assert candidate(hamsters = \"HH.H.H.H.H.H.H.H.H.H.H.H.H.H.H.H.H.H.H.H\") == -1",
    "assert candidate(hamsters = \"H.H.H.H.H.H.H.H.H.H.H.H.H.H.H\") == 8",
    "assert candidate(hamsters = \"HH.HH.HH\") == -1",
    "assert candidate(hamsters = \"H.H.H\") == 2",
    "assert candidate(hamsters = \"HH.H.H.H.H\") == -1",
    "assert candidate(hamsters = \"H.H.H.H\") == 2",
    "assert candidate(hamsters = \"HH.HH\") == -1",
    "assert candidate(hamsters = \"HH.H.H.H.H.H.H.H.H.H.H\") == -1",
    "assert candidate(hamsters = \"HH.H.H.H.H.H.H.H.H.H.H.H\") == -1",
    "assert candidate(hamsters = \".H.H.\") == 1",
    "assert candidate(hamsters = \"H.H.H.H.H.H.H.H\") == 4",
    "assert candidate(hamsters = \"H.HH\") == -1",
    "assert candidate(hamsters = \"H.H.H.H.H.H.H.H.H.H.H.H.H\") == 7",
    "assert candidate(hamsters = \"HHHHHH\") == -1",
    "assert candidate(hamsters = \"HH.H.H\") == -1",
    "assert candidate(hamsters = \"HH.H\") == -1",
    "assert candidate(hamsters = \"H.H.H.H.H.H.H.H.H\") == 5",
    "assert candidate(hamsters = \"HH.H.H.H.H.H.H\") == -1",
    "assert candidate(hamsters = \"H.H.H.H.H.H.H.H.H.H.H.H.H.H.H.H.H.H.H\") == 10",
    "assert candidate(hamsters = \"HH.H.H.H.H.H.H.H.H.H.H.H.H.H.H.H\") == -1",
    "assert candidate(hamsters = \"HH.H.HH\") == -1",
    "assert candidate(hamsters = \"......\") == 0",
    "assert candidate(hamsters = \"H.H.H.H.H.H.H.H.H.H.H\") == 6",
    "assert candidate(hamsters = \"...\") == 0",
    "assert candidate(hamsters = \"H.H.H.H.H.H.H.H.H.H.H.H.H.H.H.H.H\") == 9",
    "assert candidate(hamsters = \"H.H.HH.H.H\") == 4",
    "assert candidate(hamsters = \"H.....H\") == 2",
    "assert candidate(hamsters = \"H.H.H.H.H.H.H\") == 4",
    "assert candidate(hamsters = \"H.....H\") == 2",
    "assert candidate(hamsters = \".......\") == 0",
    "assert candidate(hamsters = \"HH.HHHHH.HH\") == -1",
    "assert candidate(hamsters = \".H.H.\") == 1",
    "assert candidate(hamsters = \"H.H.H.H.HH\") == -1",
    "assert candidate(hamsters = \"........\") == 0",
    "assert candidate(hamsters = \"H.H.H.H.H.H.H.H.H\") == 5",
    "assert candidate(hamsters = \"..H.H..\") == 1",
    "assert candidate(hamsters = \"H.H.H.H.H\") == 3",
    "assert candidate(hamsters = \"HH.H.H.HH\") == -1",
    "assert candidate(hamsters = \"HH\") == -1",
    "assert candidate(hamsters = \"H.HH.H\") == 2",
    "assert candidate(hamsters = \"HH.HH.HH.HH.HH.HH.HH.HH\") == -1",
    "assert candidate(hamsters = \"...\") == 0",
    "assert candidate(hamsters = \"H.\") == 1",
    "assert candidate(hamsters = \"H.H..H.H\") == 2",
    "assert candidate(hamsters = \"H.......H\") == 2",
    "assert candidate(hamsters = \"..H..H..\") == 2",
    "assert candidate(hamsters = \"HHHHH\") == -1",
    "assert candidate(hamsters = \"HH.HH\") == -1",
    "assert candidate(hamsters = \"HH.H.H.H.HH\") == -1",
    "assert candidate(hamsters = \"H...H\") == 2",
    "assert candidate(hamsters = \"HH.HHH.HH\") == -1",
    "assert candidate(hamsters = \"........\") == 0",
    "assert candidate(hamsters = \"H.H.H.HH.H\") == 3",
    "assert candidate(hamsters = \"HH.HH.HH.HH\") == -1",
    "assert candidate(hamsters = \"H.H.H.H\") == 2",
    "assert candidate(hamsters = \".\") == 0",
    "assert candidate(hamsters = \"HHHHHHHHHH\") == -1",
    "assert candidate(hamsters = \".HHH.\") == -1",
    "assert candidate(hamsters = \"H.H.H.HH\") == -1",
    "assert candidate(hamsters = \".H\") == 1",
    "assert candidate(hamsters = \".H.H.H.H.\") == 2",
    "assert candidate(hamsters = \"H.H.H\") == 2",
    "assert candidate(hamsters = \"H\") == -1",
    "assert candidate(hamsters = \".........\") == 0",
    "assert candidate(hamsters = \".H.H.H.H.H.H.H.H.H.\") == 5",
    "assert candidate(hamsters = \".H.H.H.H.H.H.H.H.\") == 4",
    "assert candidate(hamsters = \"HHHHHHH\") == -1",
    "assert candidate(hamsters = \"HH...HH\") == -1",
    "assert candidate(hamsters = \"H.H.H.H.H.H.H.H.H.H.H.H\") == 6",
    "assert candidate(hamsters = \"H......H\") == 2",
    "assert candidate(hamsters = \"H.H\") == 1",
    "assert candidate(hamsters = \"HH.HH.HH.HH.HH\") == -1",
    "assert candidate(hamsters = \"H..H\") == 2",
    "assert candidate(hamsters = \"HH..HH\") == -1",
    "assert candidate(hamsters = \"HHHH\") == -1"
  ]
}